[
  {
    "id": "50686122797@s.whatsapp.net",
    "name": "Teresita Cubero Maroto"
  },
  {
    "id": "50672087301@s.whatsapp.net",
    "name": "Arturo Hernandez"
  },
  {
    "id": "50672092535@s.whatsapp.net",
    "name": "Paola"
  },
  {
    "id": "50664146894@s.whatsapp.net",
    "name": "Marlon F Asesor Liberty"
  },
  {
    "id": "50670490077@s.whatsapp.net",
    "name": "Marlon Flores"
  },
  {
    "id": "50689827904@s.whatsapp.net",
    "name": "Rebeca🪷🪷"
  },
  {
    "id": "50672131962@s.whatsapp.net",
    "name": "Geraldo"
  },
  {
    "id": "50661803973@s.whatsapp.net",
    "name": "NA"
  },
  {
    "id": "50688204689@s.whatsapp.net",
    "name": "Marisol Castillo"
  },
  {
    "id": "50660509843@s.whatsapp.net",
    "name": "Jorge López"
  },
  {
    "id": "50688300821@s.whatsapp.net",
    "name": "Sandra"
  },
  {
    "id": "50684613939@s.whatsapp.net",
    "name": "Hillary A...🪷🐼"
  },
  {
    "id": "50660034660@s.whatsapp.net",
    "name": "Yohania Gonzalez"
  },
  {
    "id": "50672111621@s.whatsapp.net",
    "name": "franklin alvarado"
  },
  {
    "id": "50672132033@s.whatsapp.net",
    "name": "💪☠️😈⚽😎🤫🤨☠️☠️☠️☠️☠️"
  },
  {
    "id": "50672114145@s.whatsapp.net",
    "name": "em848536"
  },
  {
    "id": "50663399579@s.whatsapp.net",
    "name": "NA"
  },
  {
    "id": "50683245012@s.whatsapp.net",
    "name": "NA"
  },
  {
    "id": "50660596388@s.whatsapp.net",
    "name": "NA"
  },
  {
    "id": "50661331450@s.whatsapp.net",
    "name": "NA"
  },
  {
    "id": "50662086747@s.whatsapp.net",
    "name": "NA"
  },
  {
    "id": "50671023526@s.whatsapp.net",
    "name": "NA"
  },
  {
    "id": "50671023525@s.whatsapp.net",
    "name": "NA"
  },
  {
    "id": "50671023520@s.whatsapp.net",
    "name": "NA"
  },
  {
    "id": "50671023515@s.whatsapp.net",
    "name": "NA"
  },
  {
    "id": "50671023513@s.whatsapp.net",
    "name": "NA"
  },
  {
    "id": "50671023512@s.whatsapp.net",
    "name": "NA"
  },
  {
    "id": "50671023511@s.whatsapp.net",
    "name": "NA"
  },
  {
    "id": "50671023510@s.whatsapp.net",
    "name": "NA"
  },
  {
    "id": "50671023507@s.whatsapp.net",
    "name": "NA"
  },
  {
    "id": "50671023505@s.whatsapp.net",
    "name": "NA"
  },
  {
    "id": "50671023503@s.whatsapp.net",
    "name": "NA"
  },
  {
    "id": "50671023498@s.whatsapp.net",
    "name": "NA"
  },
  {
    "id": "50671023494@s.whatsapp.net",
    "name": "NA"
  },
  {
    "id": "50671023490@s.whatsapp.net",
    "name": "NA"
  },
  {
    "id": "50671023486@s.whatsapp.net",
    "name": "NA"
  },
  {
    "id": "50671023483@s.whatsapp.net",
    "name": "NA"
  },
  {
    "id": "50671023482@s.whatsapp.net",
    "name": "NA"
  },
  {
    "id": "50661040329@s.whatsapp.net",
    "name": "charlieabril15@hotmail.co"
  },
  {
    "id": "50661326134@s.whatsapp.net",
    "name": "NA"
  },
  {
    "id": "50671023480@s.whatsapp.net",
    "name": "Jorge Isaac. Calderón N"
  },
  {
    "id": "50688238374@s.whatsapp.net",
    "name": "NA"
  },
  {
    "id": "50688895781@s.whatsapp.net",
    "name": "NA"
  },
  {
    "id": "50671023468@s.whatsapp.net",
    "name": "Leylin Delgado"
  },
  {
    "id": "50671023478@s.whatsapp.net",
    "name": "NA"
  },
  {
    "id": "50671023477@s.whatsapp.net",
    "name": "NA"
  },
  {
    "id": "50671023476@s.whatsapp.net",
    "name": "NA"
  },
  {
    "id": "50671023475@s.whatsapp.net",
    "name": "NA"
  },
  {
    "id": "50671023474@s.whatsapp.net",
    "name": "NA"
  },
  {
    "id": "50671023470@s.whatsapp.net",
    "name": "NA"
  },
  {
    "id": "50671023462@s.whatsapp.net",
    "name": "NA"
  },
  {
    "id": "50671023461@s.whatsapp.net",
    "name": "NA"
  },
  {
    "id": "50671023459@s.whatsapp.net",
    "name": "NA"
  },
  {
    "id": "50671023452@s.whatsapp.net",
    "name": "NA"
  },
  {
    "id": "50672123834@s.whatsapp.net",
    "name": "alfredocardon17363"
  },
  {
    "id": "50671023427@s.whatsapp.net",
    "name": "MORALES"
  },
  {
    "id": "50671023447@s.whatsapp.net",
    "name": "NA"
  },
  {
    "id": "50671023442@s.whatsapp.net",
    "name": "NA"
  },
  {
    "id": "50671023440@s.whatsapp.net",
    "name": "NA"
  },
  {
    "id": "50671023439@s.whatsapp.net",
    "name": "NA"
  },
  {
    "id": "50671023438@s.whatsapp.net",
    "name": "NA"
  },
  {
    "id": "50671023436@s.whatsapp.net",
    "name": "NA"
  },
  {
    "id": "50671023435@s.whatsapp.net",
    "name": "NA"
  },
  {
    "id": "50671023434@s.whatsapp.net",
    "name": "NA"
  },
  {
    "id": "50671023431@s.whatsapp.net",
    "name": "NA"
  },
  {
    "id": "50671923524@s.whatsapp.net",
    "name": "DEA"
  },
  {
    "id": "50661043101@s.whatsapp.net",
    "name": "Kv Baby"
  },
  {
    "id": "50662801661@s.whatsapp.net",
    "name": "Mari"
  },
  {
    "id": "50683673518@s.whatsapp.net",
    "name": "NA"
  },
  {
    "id": "50662301135@s.whatsapp.net",
    "name": "Gio"
  },
  {
    "id": "50661329844@s.whatsapp.net",
    "name": "Lizzy Rodríguez"
  },
  {
    "id": "50689284778@s.whatsapp.net",
    "name": "NA"
  },
  {
    "id": "50661331177@s.whatsapp.net",
    "name": "NA"
  },
  {
    "id": "50683484830@s.whatsapp.net",
    "name": "NA"
  },
  {
    "id": "50683537160@s.whatsapp.net",
    "name": "NA"
  },
  {
    "id": "50671188437@s.whatsapp.net",
    "name": "S⚡B⚡"
  },
  {
    "id": "50671023424@s.whatsapp.net",
    "name": "NA"
  },
  {
    "id": "50671023423@s.whatsapp.net",
    "name": "NA"
  },
  {
    "id": "50671023422@s.whatsapp.net",
    "name": "NA"
  },
  {
    "id": "50671023417@s.whatsapp.net",
    "name": "NA"
  },
  {
    "id": "50671023416@s.whatsapp.net",
    "name": "NA"
  },
  {
    "id": "50671023412@s.whatsapp.net",
    "name": "NA"
  },
  {
    "id": "50688560843@s.whatsapp.net",
    "name": "Ana Sedy"
  },
  {
    "id": "50670107011@s.whatsapp.net",
    "name": "NA"
  },
  {
    "id": "50672093128@s.whatsapp.net",
    "name": "😆😆"
  },
  {
    "id": "50672131816@s.whatsapp.net",
    "name": "Ian"
  },
  {
    "id": "50672093130@s.whatsapp.net",
    "name": "Joha🦋"
  },
  {
    "id": "50672096189@s.whatsapp.net",
    "name": "NA"
  },
  {
    "id": "50672096181@s.whatsapp.net",
    "name": "NA"
  },
  {
    "id": "50672096179@s.whatsapp.net",
    "name": "NA"
  },
  {
    "id": "50672096176@s.whatsapp.net",
    "name": "NA"
  },
  {
    "id": "50672096173@s.whatsapp.net",
    "name": "NA"
  },
  {
    "id": "50672096169@s.whatsapp.net",
    "name": "NA"
  },
  {
    "id": "50672096168@s.whatsapp.net",
    "name": "NA"
  },
  {
    "id": "50672096166@s.whatsapp.net",
    "name": "NA"
  },
  {
    "id": "50672096163@s.whatsapp.net",
    "name": "NA"
  },
  {
    "id": "50672096160@s.whatsapp.net",
    "name": "NA"
  },
  {
    "id": "50672096159@s.whatsapp.net",
    "name": "NA"
  },
  {
    "id": "50672096154@s.whatsapp.net",
    "name": "NA"
  },
  {
    "id": "50672096152@s.whatsapp.net",
    "name": "NA"
  },
  {
    "id": "50672093147@s.whatsapp.net",
    "name": "NA"
  },
  {
    "id": "50672093146@s.whatsapp.net",
    "name": "NA"
  },
  {
    "id": "50672093145@s.whatsapp.net",
    "name": "NA"
  },
  {
    "id": "50672093143@s.whatsapp.net",
    "name": "NA"
  },
  {
    "id": "50672093139@s.whatsapp.net",
    "name": "NA"
  },
  {
    "id": "50672093134@s.whatsapp.net",
    "name": "NA"
  },
  {
    "id": "50672093133@s.whatsapp.net",
    "name": "NA"
  },
  {
    "id": "50672093132@s.whatsapp.net",
    "name": "NA"
  },
  {
    "id": "50672093126@s.whatsapp.net",
    "name": "NA"
  },
  {
    "id": "50688135336@s.whatsapp.net",
    "name": "NA"
  },
  {
    "id": "50672092824@s.whatsapp.net",
    "name": "NA"
  },
  {
    "id": "50672092821@s.whatsapp.net",
    "name": "NA"
  },
  {
    "id": "50672092818@s.whatsapp.net",
    "name": "NA"
  },
  {
    "id": "50672092811@s.whatsapp.net",
    "name": "NA"
  },
  {
    "id": "50672092799@s.whatsapp.net",
    "name": "NA"
  },
  {
    "id": "50672092798@s.whatsapp.net",
    "name": "NA"
  },
  {
    "id": "50672092797@s.whatsapp.net",
    "name": "NA"
  },
  {
    "id": "50672092795@s.whatsapp.net",
    "name": "NA"
  },
  {
    "id": "50672092794@s.whatsapp.net",
    "name": "NA"
  },
  {
    "id": "50672092792@s.whatsapp.net",
    "name": "NA"
  },
  {
    "id": "50672092788@s.whatsapp.net",
    "name": "NA"
  },
  {
    "id": "50672092786@s.whatsapp.net",
    "name": "NA"
  },
  {
    "id": "50672092784@s.whatsapp.net",
    "name": "NA"
  },
  {
    "id": "50672092778@s.whatsapp.net",
    "name": "NA"
  },
  {
    "id": "50672092177@s.whatsapp.net",
    "name": "Mari Salazar"
  },
  {
    "id": "50672064445@s.whatsapp.net",
    "name": "NA"
  },
  {
    "id": "50660466151@s.whatsapp.net",
    "name": "Karii"
  },
  {
    "id": "50672092532@s.whatsapp.net",
    "name": "JordiQM🇨🇷🚲"
  },
  {
    "id": "50672092573@s.whatsapp.net",
    "name": "NA"
  },
  {
    "id": "50672092565@s.whatsapp.net",
    "name": "Heiner PG"
  },
  {
    "id": "50672092572@s.whatsapp.net",
    "name": "NA"
  },
  {
    "id": "50672092568@s.whatsapp.net",
    "name": "NA"
  },
  {
    "id": "50672092553@s.whatsapp.net",
    "name": "Andrés Peña"
  },
  {
    "id": "50672092552@s.whatsapp.net",
    "name": "NA"
  },
  {
    "id": "50672092547@s.whatsapp.net",
    "name": "NA"
  },
  {
    "id": "50672092545@s.whatsapp.net",
    "name": "NA"
  },
  {
    "id": "50672092543@s.whatsapp.net",
    "name": "NA"
  },
  {
    "id": "50672092541@s.whatsapp.net",
    "name": "NA"
  },
  {
    "id": "50672092536@s.whatsapp.net",
    "name": "NA"
  },
  {
    "id": "50672092531@s.whatsapp.net",
    "name": "NA"
  },
  {
    "id": "50672092527@s.whatsapp.net",
    "name": "NA"
  },
  {
    "id": "50671034772@s.whatsapp.net",
    "name": "Josué Serrano Taylor"
  },
  {
    "id": "50672092339@s.whatsapp.net",
    "name": "Joseph"
  },
  {
    "id": "50672092423@s.whatsapp.net",
    "name": "NA"
  },
  {
    "id": "50672092419@s.whatsapp.net",
    "name": "NA"
  },
  {
    "id": "50672092418@s.whatsapp.net",
    "name": "NA"
  },
  {
    "id": "50672092413@s.whatsapp.net",
    "name": "NA"
  },
  {
    "id": "50672092412@s.whatsapp.net",
    "name": "NA"
  },
  {
    "id": "50672092411@s.whatsapp.net",
    "name": "NA"
  },
  {
    "id": "50672092409@s.whatsapp.net",
    "name": "NA"
  },
  {
    "id": "50672092406@s.whatsapp.net",
    "name": "NA"
  },
  {
    "id": "50672092404@s.whatsapp.net",
    "name": "NA"
  },
  {
    "id": "50672092402@s.whatsapp.net",
    "name": "NA"
  },
  {
    "id": "50672092398@s.whatsapp.net",
    "name": "NA"
  },
  {
    "id": "50672092393@s.whatsapp.net",
    "name": "NA"
  },
  {
    "id": "50672092392@s.whatsapp.net",
    "name": "NA"
  },
  {
    "id": "50672092387@s.whatsapp.net",
    "name": "NA"
  },
  {
    "id": "50672092386@s.whatsapp.net",
    "name": "NA"
  },
  {
    "id": "50672092383@s.whatsapp.net",
    "name": "NA"
  },
  {
    "id": "50672092380@s.whatsapp.net",
    "name": "NA"
  },
  {
    "id": "50672092377@s.whatsapp.net",
    "name": "NA"
  },
  {
    "id": "50672092376@s.whatsapp.net",
    "name": "NA"
  },
  {
    "id": "50672092374@s.whatsapp.net",
    "name": "NA"
  },
  {
    "id": "50672092372@s.whatsapp.net",
    "name": "NA"
  },
  {
    "id": "50672092369@s.whatsapp.net",
    "name": "NA"
  },
  {
    "id": "50672092362@s.whatsapp.net",
    "name": "NA"
  },
  {
    "id": "50672092356@s.whatsapp.net",
    "name": "NA"
  },
  {
    "id": "50672092354@s.whatsapp.net",
    "name": "NA"
  },
  {
    "id": "50672092349@s.whatsapp.net",
    "name": "NA"
  },
  {
    "id": "50672092348@s.whatsapp.net",
    "name": "NA"
  },
  {
    "id": "50672092344@s.whatsapp.net",
    "name": "NA"
  },
  {
    "id": "50672092343@s.whatsapp.net",
    "name": "NA"
  },
  {
    "id": "50672092340@s.whatsapp.net",
    "name": "NA"
  },
  {
    "id": "50672092337@s.whatsapp.net",
    "name": "NA"
  },
  {
    "id": "50672092336@s.whatsapp.net",
    "name": "NA"
  },
  {
    "id": "50672092332@s.whatsapp.net",
    "name": "NA"
  },
  {
    "id": "50672092327@s.whatsapp.net",
    "name": "NA"
  },
  {
    "id": "50672092172@s.whatsapp.net",
    "name": "David 🥊"
  },
  {
    "id": "50672092221@s.whatsapp.net",
    "name": "NA"
  },
  {
    "id": "50672092220@s.whatsapp.net",
    "name": "NA"
  },
  {
    "id": "50672092218@s.whatsapp.net",
    "name": "NA"
  },
  {
    "id": "50672092212@s.whatsapp.net",
    "name": "NA"
  },
  {
    "id": "50672092211@s.whatsapp.net",
    "name": "NA"
  },
  {
    "id": "50672092210@s.whatsapp.net",
    "name": "NA"
  },
  {
    "id": "50672092208@s.whatsapp.net",
    "name": "NA"
  },
  {
    "id": "50672092204@s.whatsapp.net",
    "name": "NA"
  },
  {
    "id": "50672092202@s.whatsapp.net",
    "name": "NA"
  },
  {
    "id": "50672092201@s.whatsapp.net",
    "name": "NA"
  },
  {
    "id": "50672092191@s.whatsapp.net",
    "name": "NA"
  },
  {
    "id": "50672092188@s.whatsapp.net",
    "name": "NA"
  },
  {
    "id": "50672092185@s.whatsapp.net",
    "name": "NA"
  },
  {
    "id": "50672092182@s.whatsapp.net",
    "name": "NA"
  },
  {
    "id": "50672092180@s.whatsapp.net",
    "name": "NA"
  },
  {
    "id": "50672092179@s.whatsapp.net",
    "name": "NA"
  },
  {
    "id": "50672092178@s.whatsapp.net",
    "name": "NA"
  },
  {
    "id": "50672092170@s.whatsapp.net",
    "name": "NA"
  },
  {
    "id": "50672092168@s.whatsapp.net",
    "name": "NA"
  },
  {
    "id": "50672092166@s.whatsapp.net",
    "name": "NA"
  },
  {
    "id": "50672092161@s.whatsapp.net",
    "name": "NA"
  },
  {
    "id": "50671034913@s.whatsapp.net",
    "name": "Juan"
  },
  {
    "id": "50672092157@s.whatsapp.net",
    "name": "NA"
  },
  {
    "id": "50672092152@s.whatsapp.net",
    "name": "NA"
  },
  {
    "id": "50671034924@s.whatsapp.net",
    "name": "NA"
  },
  {
    "id": "50671034921@s.whatsapp.net",
    "name": "NA"
  },
  {
    "id": "50671034919@s.whatsapp.net",
    "name": "NA"
  },
  {
    "id": "50671034918@s.whatsapp.net",
    "name": "NA"
  },
  {
    "id": "50671034916@s.whatsapp.net",
    "name": "NA"
  },
  {
    "id": "50671034911@s.whatsapp.net",
    "name": "NA"
  },
  {
    "id": "50671034909@s.whatsapp.net",
    "name": "NA"
  },
  {
    "id": "50671034905@s.whatsapp.net",
    "name": "NA"
  },
  {
    "id": "50671034903@s.whatsapp.net",
    "name": "NA"
  },
  {
    "id": "50671034901@s.whatsapp.net",
    "name": "NA"
  },
  {
    "id": "50672111725@s.whatsapp.net",
    "name": "Miguel"
  },
  {
    "id": "50671034779@s.whatsapp.net",
    "name": "NA"
  },
  {
    "id": "50671034775@s.whatsapp.net",
    "name": "NA"
  },
  {
    "id": "50671034774@s.whatsapp.net",
    "name": "NA"
  },
  {
    "id": "50671034773@s.whatsapp.net",
    "name": "NA"
  },
  {
    "id": "50671034766@s.whatsapp.net",
    "name": "NA"
  },
  {
    "id": "50671034764@s.whatsapp.net",
    "name": "NA"
  },
  {
    "id": "50671034763@s.whatsapp.net",
    "name": "NA"
  },
  {
    "id": "50672133550@s.whatsapp.net",
    "name": "Jossias Montero"
  },
  {
    "id": "50662097799@s.whatsapp.net",
    "name": "NA"
  },
  {
    "id": "50671034573@s.whatsapp.net",
    "name": "NA"
  },
  {
    "id": "50671034567@s.whatsapp.net",
    "name": "NA"
  },
  {
    "id": "50671034564@s.whatsapp.net",
    "name": "NA"
  },
  {
    "id": "50671034560@s.whatsapp.net",
    "name": "NA"
  },
  {
    "id": "50671034558@s.whatsapp.net",
    "name": "NA"
  },
  {
    "id": "50671034553@s.whatsapp.net",
    "name": "NA"
  },
  {
    "id": "50671034552@s.whatsapp.net",
    "name": "NA"
  },
  {
    "id": "50671034550@s.whatsapp.net",
    "name": "NA"
  },
  {
    "id": "0@s.whatsapp.net",
    "name": "NA"
  },
  {
    "id": "50671034367@s.whatsapp.net",
    "name": "NA"
  },
  {
    "id": "50671034366@s.whatsapp.net",
    "name": "NA"
  },
  {
    "id": "50671034364@s.whatsapp.net",
    "name": "NA"
  },
  {
    "id": "50671034363@s.whatsapp.net",
    "name": "NA"
  },
  {
    "id": "50661806310@s.whatsapp.net",
    "name": "Luis Calderón"
  },
  {
    "id": "50663179535@s.whatsapp.net",
    "name": "Distribuidor Autorizado"
  },
  {
    "id": "50660706253@s.whatsapp.net",
    "name": "Lizzy Rodríguez"
  },
  {
    "id": "50661327729@s.whatsapp.net",
    "name": "Distribuidor Autorizado"
  },
  {
    "id": "50661328350@s.whatsapp.net",
    "name": "Daniela Ramírez A"
  },
  {
    "id": "50661329621@s.whatsapp.net",
    "name": "Hillary Arauz DistLiberty"
  },
  {
    "id": "50661329973@s.whatsapp.net",
    "name": "telemercadeonargallo"
  },
  {
    "id": "50661332512@s.whatsapp.net",
    "name": "Liberty"
  },
  {
    "id": "50685085825@s.whatsapp.net",
    "name": "Colocha 🌙"
  },
  {
    "id": "50661335870@s.whatsapp.net",
    "name": "Hillary Asesora Liberty"
  },
  {
    "id": "50661325267@s.whatsapp.net",
    "name": "Lizzy Rodríguez"
  },
  {
    "id": "50661325722@s.whatsapp.net",
    "name": "Lizzy Rodríguez"
  },
  {
    "id": "50661327136@s.whatsapp.net",
    "name": "lizzyrodriguez"
  },
  {
    "id": "50661323326@s.whatsapp.net",
    "name": "Marco Correa Asesor"
  },
  {
    "id": "50661330233@s.whatsapp.net",
    "name": "Marco Correa Asesor"
  },
  {
    "id": "50661335778@s.whatsapp.net",
    "name": "Asesora autorizada libert"
  },
  {
    "id": "50661511298@s.whatsapp.net",
    "name": "González"
  },
  {
    "id": "50664491940@s.whatsapp.net",
    "name": "Sharon"
  },
  {
    "id": "50660212190@s.whatsapp.net",
    "name": "Daryl"
  },
  {
    "id": "50663452932@s.whatsapp.net",
    "name": "Kim✨"
  },
  {
    "id": "50688042001@s.whatsapp.net",
    "name": "Fiorela"
  },
  {
    "id": "50687323698@s.whatsapp.net",
    "name": "María José"
  },
  {
    "id": "50662268935@s.whatsapp.net",
    "name": "Marco"
  },
  {
    "id": "50670993954@s.whatsapp.net",
    "name": "Mónica Urbina"
  },
  {
    "id": "50664565839@s.whatsapp.net",
    "name": "Aarón J.R."
  },
  {
    "id": "50661673135@s.whatsapp.net",
    "name": "javier rojas"
  },
  {
    "id": "50660225160@s.whatsapp.net",
    "name": "Ileana (Fruno Logística)"
  },
  {
    "id": "50663961001@s.whatsapp.net",
    "name": "Joshua (Fruno Logística)"
  },
  {
    "id": "50660987734@s.whatsapp.net",
    "name": "ORLANDO MOYA FRUNO"
  },
  {
    "id": "50663653339@s.whatsapp.net",
    "name": "Logística Fruno Guanacast"
  },
  {
    "id": "50661751005@s.whatsapp.net",
    "name": "Fruno Logistica"
  },
  {
    "id": "50663996863@s.whatsapp.net",
    "name": "Kenneth Fruno"
  },
  {
    "id": "50661328498@s.whatsapp.net",
    "name": "Kimberly Liberty CR"
  },
  {
    "id": "50660454126@s.whatsapp.net",
    "name": "Logística Fruno"
  },
  {
    "id": "50660117276@s.whatsapp.net",
    "name": "Fruno Logistica"
  },
  {
    "id": "50660535330@s.whatsapp.net",
    "name": "Juan Carlos Villalobos"
  },
  {
    "id": "50662603285@s.whatsapp.net",
    "name": "Javier (Logística Fruno)"
  },
  {
    "id": "50664777156@s.whatsapp.net",
    "name": "Randall S C"
  },
  {
    "id": "50664182695@s.whatsapp.net",
    "name": "Fruno Logística Luis"
  },
  {
    "id": "50661231837@s.whatsapp.net",
    "name": "Fruno Zona Sur"
  },
  {
    "id": "50662546735@s.whatsapp.net",
    "name": "Douglas"
  },
  {
    "id": "50662495074@s.whatsapp.net",
    "name": "Fruno CR Logística"
  },
  {
    "id": "50672100326@s.whatsapp.net",
    "name": "mirinda"
  }
]