[
  {
    "id": "50663437316@s.whatsapp.net",
    "name": "Mi Princesita🥰"
  },
  {
    "id": "50670840076@s.whatsapp.net",
    "name": "Bley"
  },
  {
    "id": "50664062821@s.whatsapp.net",
    "name": "Cherry"
  },
  {
    "id": "50664015370@s.whatsapp.net",
    "name": "Valeria Gollo"
  },
  {
    "id": "50684599161@s.whatsapp.net",
    "name": "Switch Con Garantia"
  },
  {
    "id": "50589064140@s.whatsapp.net",
    "name": "Carlitos Primo"
  },
  {
    "id": "50683189558@s.whatsapp.net",
    "name": "Tío Eliab"
  },
  {
    "id": "50686293881@s.whatsapp.net",
    "name": "MM Alajuela 2"
  },
  {
    "id": "50686273718@s.whatsapp.net",
    "name": "Vivi Migra"
  },
  {
    "id": "50670972809@s.whatsapp.net",
    "name": "San Pedro De Barva"
  },
  {
    "id": "50662635222@s.whatsapp.net",
    "name": "Vini"
  },
  {
    "id": "50660938959@s.whatsapp.net",
    "name": "Sebis"
  },
  {
    "id": "50662295339@s.whatsapp.net",
    "name": "Ronald Muñoz"
  },
  {
    "id": "50689673146@s.whatsapp.net",
    "name": "Gisella Montero Varela"
  },
  {
    "id": "50664491940@s.whatsapp.net",
    "name": "Sharon Fruno"
  },
  {
    "id": "50687323698@s.whatsapp.net",
    "name": "María José Fruno"
  },
  {
    "id": "50662646931@s.whatsapp.net",
    "name": "Mary Alvarado Voca"
  },
  {
    "id": "50689083527@s.whatsapp.net",
    "name": "Ash La Piedad"
  },
  {
    "id": "50670769189@s.whatsapp.net",
    "name": "Camisas"
  },
  {
    "id": "50660803089@s.whatsapp.net",
    "name": "Mila"
  },
  {
    "id": "50671577369@s.whatsapp.net",
    "name": "Dragon Ink Heredia"
  },
  {
    "id": "50661709517@s.whatsapp.net",
    "name": "Nico"
  },
  {
    "id": "50664204776@s.whatsapp.net",
    "name": "Pizza House Carrillos"
  },
  {
    "id": "50661558553@s.whatsapp.net",
    "name": "Hans"
  },
  {
    "id": "50663762728@s.whatsapp.net",
    "name": "César Romero"
  },
  {
    "id": "50661295900@s.whatsapp.net",
    "name": "Key Sister"
  },
  {
    "id": "50672740369@s.whatsapp.net",
    "name": "Vale Voca"
  },
  {
    "id": "50670520332@s.whatsapp.net",
    "name": "Switch Zelda"
  },
  {
    "id": "50689612120@s.whatsapp.net",
    "name": "Cafetería Grecja"
  },
  {
    "id": "50660791340@s.whatsapp.net",
    "name": "Jorge"
  },
  {
    "id": "50687436177@s.whatsapp.net",
    "name": "MM GRECIA"
  },
  {
    "id": "50686768850@s.whatsapp.net",
    "name": "Alquiler Apartamento"
  },
  {
    "id": "50662029867@s.whatsapp.net",
    "name": "Karol Parce"
  },
  {
    "id": "50661511298@s.whatsapp.net",
    "name": "Allison💙"
  },
  {
    "id": "50687420855@s.whatsapp.net",
    "name": "MM Heredia"
  },
  {
    "id": "50660179555@s.whatsapp.net",
    "name": "Boligrafos"
  },
  {
    "id": "50686113310@s.whatsapp.net",
    "name": "Eveling Vecina"
  },
  {
    "id": "50683633540@s.whatsapp.net",
    "name": "Sonia Tribuna"
  },
  {
    "id": "50662153420@s.whatsapp.net",
    "name": "Pizza House San Roque"
  },
  {
    "id": "50663592496@s.whatsapp.net",
    "name": "Kaylita"
  },
  {
    "id": "34612410639@s.whatsapp.net",
    "name": "Tia Reina"
  },
  {
    "id": "50662779477@s.whatsapp.net",
    "name": "saymond Voca"
  },
  {
    "id": "50688757219@s.whatsapp.net",
    "name": "Hazel Antigua Oficinista"
  },
  {
    "id": "50687735751@s.whatsapp.net",
    "name": "Maria Jose Gollo"
  },
  {
    "id": "50688829010@s.whatsapp.net",
    "name": "Brayan Monge"
  },
  {
    "id": "50670139204@s.whatsapp.net",
    "name": "Gracia"
  },
  {
    "id": "50664900774@s.whatsapp.net",
    "name": "Katherine"
  },
  {
    "id": "50663079357@s.whatsapp.net",
    "name": "Axel Unicomer"
  },
  {
    "id": "50663310851@s.whatsapp.net",
    "name": "Jessica La Piedad"
  },
  {
    "id": "50670409388@s.whatsapp.net",
    "name": "Angi3"
  },
  {
    "id": "50684252819@s.whatsapp.net",
    "name": "María José Fruno"
  },
  {
    "id": "50683239492@s.whatsapp.net",
    "name": "Jorge Jimenez Aperturas"
  },
  {
    "id": "50662343368@s.whatsapp.net",
    "name": "Ana Calvo Flores"
  },
  {
    "id": "50689788585@s.whatsapp.net",
    "name": "Mira Flores"
  },
  {
    "id": "50671924259@s.whatsapp.net",
    "name": "Rosibel"
  },
  {
    "id": "50688161205@s.whatsapp.net",
    "name": "Priscilla Rojas Ccpcr"
  },
  {
    "id": "50687029621@s.whatsapp.net",
    "name": "Raque Artavia CCPCR"
  },
  {
    "id": "50663423676@s.whatsapp.net",
    "name": "Fernanda"
  },
  {
    "id": "50671173636@s.whatsapp.net",
    "name": "Ashely"
  },
  {
    "id": "50662620039@s.whatsapp.net",
    "name": "Muebleria Krisval"
  },
  {
    "id": "50688050298@s.whatsapp.net",
    "name": "Francasio"
  },
  {
    "id": "50689919798@s.whatsapp.net",
    "name": "Hannia Colegio"
  },
  {
    "id": "50685544479@s.whatsapp.net",
    "name": "Esteban Voca"
  },
  {
    "id": "50671908101@s.whatsapp.net",
    "name": "Juanka Arias"
  },
  {
    "id": "50689858794@s.whatsapp.net",
    "name": "Jereline"
  },
  {
    "id": "50670221073@s.whatsapp.net",
    "name": "Consejo Regional Heredia"
  },
  {
    "id": "50661721704@s.whatsapp.net",
    "name": "Toño"
  },
  {
    "id": "50684448411@s.whatsapp.net",
    "name": "Milena"
  },
  {
    "id": "50683050151@s.whatsapp.net",
    "name": "Grettel De Lemos"
  },
  {
    "id": "50688042001@s.whatsapp.net",
    "name": "Fiorela Fruno💙"
  },
  {
    "id": "50664088504@s.whatsapp.net",
    "name": "Angela Alvarado"
  },
  {
    "id": "50663843709@s.whatsapp.net",
    "name": "Kenry"
  },
  {
    "id": "50688285716@s.whatsapp.net",
    "name": "Jorge Jimenez Aperturas"
  },
  {
    "id": "50670204051@s.whatsapp.net",
    "name": "Alba Seguridad"
  },
  {
    "id": "50688618441@s.whatsapp.net",
    "name": "Gloria Reco Fune"
  },
  {
    "id": "50670430955@s.whatsapp.net",
    "name": "Delicias Panda"
  },
  {
    "id": "50684804031@s.whatsapp.net",
    "name": "Grados"
  },
  {
    "id": "50688362483@s.whatsapp.net",
    "name": "Ivania"
  },
  {
    "id": "50685774689@s.whatsapp.net",
    "name": "Fabi Hermana Lis"
  },
  {
    "id": "50663803192@s.whatsapp.net",
    "name": "Jenny"
  },
  {
    "id": "50686147814@s.whatsapp.net",
    "name": "Leti Suegra"
  },
  {
    "id": "50688732355@s.whatsapp.net",
    "name": "Meylin"
  },
  {
    "id": "50661574714@s.whatsapp.net",
    "name": "Cris Old"
  },
  {
    "id": "50686168203@s.whatsapp.net",
    "name": "Ivania"
  },
  {
    "id": "50662658007@s.whatsapp.net",
    "name": "Jean"
  },
  {
    "id": "50578757638@s.whatsapp.net",
    "name": "Ismael"
  },
  {
    "id": "50660761426@s.whatsapp.net",
    "name": "Dayana La Piedad"
  },
  {
    "id": "50661662775@s.whatsapp.net",
    "name": "Andrey"
  },
  {
    "id": "50661340554@s.whatsapp.net",
    "name": "Cuñis💖"
  },
  {
    "id": "50672018597@s.whatsapp.net",
    "name": "Ofice Deppot Heredia"
  },
  {
    "id": "50684178528@s.whatsapp.net",
    "name": "Hillary"
  },
  {
    "id": "50686396923@s.whatsapp.net",
    "name": "Marco Apartamentos"
  },
  {
    "id": "50664152159@s.whatsapp.net",
    "name": "Elisa"
  },
  {
    "id": "50661414571@s.whatsapp.net",
    "name": "Apartamento Grecia"
  },
  {
    "id": "50662454178@s.whatsapp.net",
    "name": "Katia Suegra"
  },
  {
    "id": "50686414646@s.whatsapp.net",
    "name": "MM Alajuela Centro"
  },
  {
    "id": "50664040580@s.whatsapp.net",
    "name": "Lis Voca"
  },
  {
    "id": "50686501881@s.whatsapp.net",
    "name": "Rosvil Carrillos"
  },
  {
    "id": "50661576837@s.whatsapp.net",
    "name": "Karla Piedad"
  },
  {
    "id": "50660605919@s.whatsapp.net",
    "name": "Andrea Gonzalez"
  },
  {
    "id": "50685278930@s.whatsapp.net",
    "name": "Padias"
  },
  {
    "id": "50581897549@s.whatsapp.net",
    "name": "Abue"
  },
  {
    "id": "50686610303@s.whatsapp.net",
    "name": "103"
  },
  {
    "id": "50661168109@s.whatsapp.net",
    "name": "Deyner Revo"
  },
  {
    "id": "50621046336@s.whatsapp.net",
    "name": "Popular"
  },
  {
    "id": "50671365288@s.whatsapp.net",
    "name": "Milca"
  },
  {
    "id": "50660213523@s.whatsapp.net",
    "name": "James"
  },
  {
    "id": "50689806725@s.whatsapp.net",
    "name": "Ale Muebleria"
  },
  {
    "id": "50660041545@s.whatsapp.net",
    "name": "Lagar"
  },
  {
    "id": "50664757155@s.whatsapp.net",
    "name": "La Piedad"
  },
  {
    "id": "50689700428@s.whatsapp.net",
    "name": "Jeffry Aux Tse"
  },
  {
    "id": "50670816800@s.whatsapp.net",
    "name": "Jackeline Comida Piedad"
  },
  {
    "id": "50683445230@s.whatsapp.net",
    "name": "Eli Brunca"
  },
  {
    "id": "50660461394@s.whatsapp.net",
    "name": "ICU MEDICAL"
  },
  {
    "id": "50683699210@s.whatsapp.net",
    "name": "Apartamentos"
  },
  {
    "id": "50662066022@s.whatsapp.net",
    "name": "Yara Ofical"
  },
  {
    "id": "50663291132@s.whatsapp.net",
    "name": "Sheila Old"
  },
  {
    "id": "50662487218@s.whatsapp.net",
    "name": "Keneth Piedad"
  },
  {
    "id": "50685458545@s.whatsapp.net",
    "name": "Jose Voca"
  },
  {
    "id": "50687919144@s.whatsapp.net",
    "name": "Casa El Jocote"
  },
  {
    "id": "50683402867@s.whatsapp.net",
    "name": "Antonio Charla"
  },
  {
    "id": "50687422317@s.whatsapp.net",
    "name": "MARTA Voca"
  },
  {
    "id": "50671348189@s.whatsapp.net",
    "name": "Joss"
  },
  {
    "id": "50687826049@s.whatsapp.net",
    "name": "Sam"
  },
  {
    "id": "50688009220@s.whatsapp.net",
    "name": "Lili"
  },
  {
    "id": "50684027679@s.whatsapp.net",
    "name": "Fergie Orozco"
  },
  {
    "id": "50686958006@s.whatsapp.net",
    "name": "Jp"
  },
  {
    "id": "50686340429@s.whatsapp.net",
    "name": "Brayan"
  },
  {
    "id": "50662138654@s.whatsapp.net",
    "name": "Pizza House Poas"
  },
  {
    "id": "50686888535@s.whatsapp.net",
    "name": "Katherine Fruno"
  },
  {
    "id": "50672706081@s.whatsapp.net",
    "name": "Liliana Apertura"
  },
  {
    "id": "50683183098@s.whatsapp.net",
    "name": "Profe Invu"
  },
  {
    "id": "50684633323@s.whatsapp.net",
    "name": "Berni Jefe"
  },
  {
    "id": "13477331635@s.whatsapp.net",
    "name": "Papito"
  },
  {
    "id": "50683238341@s.whatsapp.net",
    "name": "Angela Comida"
  },
  {
    "id": "50662001380@s.whatsapp.net",
    "name": "Jorge"
  },
  {
    "id": "50671796467@s.whatsapp.net",
    "name": "Mamita"
  },
  {
    "id": "50683675335@s.whatsapp.net",
    "name": "Wendy"
  }
]